piaf/__init__.py
piaf/agent.py
piaf/api/__init__.py
piaf/api/config.py
piaf/api/controllers.py
piaf/api/dependencies.py
piaf/api/exceptions.py
piaf/api/impl/__init__.py
piaf/api/impl/process.py
piaf/api/impl/tasks.py
piaf/api/models.py
piaf/api/routes.py
piaf/audit.py
piaf/behavior.py
piaf/comm/__init__.py
piaf/comm/mtp/amqp.py
piaf/comm/mts.py
piaf/examples/benchmarks/empty_agents.py
piaf/examples/heavycomm.py
piaf/examples/helloworld.py
piaf/examples/pingpong.py
piaf/examples/two_platforms/ptf1.py
piaf/examples/two_platforms/ptf2.py
piaf/examples/useams.py
piaf/examples/usedf.py
piaf/exceptions.py
piaf/launcher.py
piaf/platform.py
piaf/ptf.py
piaf/py.typed
piaf/service.py
piaf/util.py
piaf-0.2.1.dist-info/LICENSE
piaf-0.2.1.dist-info/METADATA
piaf-0.2.1.dist-info/WHEEL
piaf-0.2.1.dist-info/RECORD
