Metadata-Version: 2.1
Name: piaf
Version: 0.2.1
Summary: A FIPA-compliant Agent Platform written in python.
Home-page: https://gitlab.com/ornythorinque/piaf
License: MIT
Keywords: Python Agent Framework,multi-agent,asyncio
Author: Pierre DUBAILLAY
Author-email: pierredubaillay@outlook.fr
Requires-Python: >=3.7,<4
Classifier: License :: OSI Approved :: MIT License
Classifier: Programming Language :: Python :: 3
Classifier: Programming Language :: Python :: 3.7
Classifier: Programming Language :: Python :: 3.8
Classifier: Programming Language :: Python :: 3.9
Classifier: Programming Language :: Python :: 3.10
Classifier: Programming Language :: Python :: 3.11
Provides-Extra: amqp-mtp
Provides-Extra: webapi
Requires-Dist: aioredis (>=2,<3) ; extra == "webapi"
Requires-Dist: aiormq (>=6,<7) ; extra == "amqp-mtp"
Requires-Dist: async-timeout (>=4,<5) ; extra == "webapi"
Requires-Dist: fastapi (>=0.92,<0.93) ; extra == "webapi"
Requires-Dist: python-dotenv (>=0.21,<0.22)
Requires-Dist: semver (>=2,<3)
Requires-Dist: yarl (>=1,<2) ; extra == "amqp-mtp"
Project-URL: Repository, https://gitlab.com/ornythorinque/piaf
